pganalytics/__init__.py
pganalytics/utils.py
pganalytics-1.0.19.dist-info/METADATA
pganalytics-1.0.19.dist-info/WHEEL
pganalytics-1.0.19.dist-info/top_level.txt
pganalytics-1.0.19.dist-info/RECORD
