Metadata-Version: 2.4
Name: pganalytics
Version: 1.0.19
Summary: A Python library for analyzing PG data
Home-page: 
Author: pgcass
Author-email: cansin@pronetgaming.com
Classifier: Programming Language :: Python :: 3
Classifier: License :: OSI Approved :: MIT License
Classifier: Operating System :: OS Independent
Requires-Python: >=3.6
Requires-Dist: pandas
Requires-Dist: google-cloud-bigquery==3.31.0
Requires-Dist: xgboost
Requires-Dist: scikit-learn
Requires-Dist: pyyaml
Requires-Dist: google-generativeai==0.8.4
Requires-Dist: db-dtypes
Requires-Dist: xlsxwriter
Requires-Dist: pendulum
Requires-Dist: sqlalchemy<3.0,>=2.0
Requires-Dist: prefect==3.4.11
Requires-Dist: prefect-email==0.4.2
Dynamic: author
Dynamic: author-email
Dynamic: classifier
Dynamic: description
Dynamic: description-content-type
Dynamic: requires-dist
Dynamic: requires-python
Dynamic: summary
